scrapegraphaisub/__init__.py
scrapegraphaisub/builders/__init__.py
scrapegraphaisub/builders/graph_builder.py
scrapegraphaisub/evaluators/__init__.py
scrapegraphaisub/evaluators/trulens_evaluator.py
scrapegraphaisub/graphs/__init__.py
scrapegraphaisub/graphs/base_graph.py
scrapegraphaisub/graphs/smart_scraper_graph.py
scrapegraphaisub/graphs/speech_graph.py
scrapegraphaisub/helpers/__init__.py
scrapegraphaisub/helpers/models_tokens.py
scrapegraphaisub/helpers/nodes_metadata.py
scrapegraphaisub/helpers/schemas.py
scrapegraphaisub/models/__init__.py
scrapegraphaisub/models/gemini.py
scrapegraphaisub/models/openai.py
scrapegraphaisub/models/openai_itt.py
scrapegraphaisub/models/openai_tts.py
scrapegraphaisub/nodes/__init__.py
scrapegraphaisub/nodes/base_node.py
scrapegraphaisub/nodes/conditional_node.py
scrapegraphaisub/nodes/fetch_node.py
scrapegraphaisub/nodes/generate_answer_node.py
scrapegraphaisub/nodes/get_probable_tags_node.py
scrapegraphaisub/nodes/image_to_text_node.py
scrapegraphaisub/nodes/parse_node.py
scrapegraphaisub/nodes/rag_node.py
scrapegraphaisub/nodes/text_to_speech_node.py
scrapegraphaisub/utils/__init__.py
scrapegraphaisub/utils/convert_to_csv.py
scrapegraphaisub/utils/convert_to_json.py
scrapegraphaisub/utils/parse_state_keys.py
scrapegraphaisub/utils/remover.py
scrapegraphaisub/utils/save_audio_from_bytes.py
scrapegraphaisub/utils/test_node.py
scrapegraphaisub/utils/token_calculator.py
scrapegraphaisub-0.0.12b4.dist-info/LICENSE
scrapegraphaisub-0.0.12b4.dist-info/METADATA
scrapegraphaisub-0.0.12b4.dist-info/WHEEL
scrapegraphaisub-0.0.12b4.dist-info/RECORD
