Metadata-Version: 2.1
Name: scrapegraphaisub
Version: 0.0.12b4
Summary: A first semantic versioned Scrapegraph fork by subzero team
Home-page: https://github.com/subzero-team/Scrapegraph-ai
License: MIT
Keywords: scrapegraph,scrapegraphai,langchain,ai,artificial intelligence,gpt,machine learning,rag,nlp,natural language processing,openai,scraping,web scraping,web scraping library,web scraping tool,webscraping,graph
Author: simone pulcini
Author-email: pulcini@prova.prova
Requires-Python: >=3.9, !=2.7.*, !=3.0.*, !=3.1.*, !=3.2.*, !=3.3.*, !=3.4.*, !=3.5.*, !=3.6.*, !=3.7.*, !=3.8.*, !=3.12.*
Classifier: Intended Audience :: Developers
Classifier: License :: OSI Approved :: MIT License
Classifier: Operating System :: OS Independent
Classifier: Programming Language :: Python :: 3
Classifier: Programming Language :: Python :: 3.10
Classifier: Programming Language :: Python :: 3.11
Classifier: Topic :: Software Development :: Libraries :: Python Modules
Requires-Dist: beautifulsoup4 (==4.12.3)
Requires-Dist: faiss-cpu (==1.7.4)
Requires-Dist: graphviz (==0.20.1)
Requires-Dist: html2text (==2020.1.16)
Requires-Dist: langchain (==0.1.6)
Requires-Dist: langchain_community (==0.0.19)
Requires-Dist: langchain_core (==0.1.22)
Requires-Dist: langchain_google_genai (==0.0.11)
Requires-Dist: langchain_openai (==0.0.5)
Requires-Dist: pandas (==2.0.3)
Requires-Dist: python-dotenv (==1.0.1)
Requires-Dist: tiktoken (>=0.5.2,<0.6.0)
Requires-Dist: tqdm (==4.66.1)
Requires-Dist: trulens_eval (==0.23.0)
Project-URL: Documentation, https://github.com/subzero-team/Scrapegraph-ai
Project-URL: Repository, https://github.com/subzero-team/Scrapegraph-ai
